flask_cognito_extended/__init__.py
flask_cognito_extended/cognito_manager.py
flask_cognito_extended/config.py
flask_cognito_extended/decorators.py
flask_cognito_extended/default_callbacks.py
flask_cognito_extended/exceptions.py
flask_cognito_extended/tokens.py
flask_cognito_extended/utils.py
Flask_Cognito_Extended-0.2.7.dist-info/LICENSE
Flask_Cognito_Extended-0.2.7.dist-info/METADATA
Flask_Cognito_Extended-0.2.7.dist-info/WHEEL
Flask_Cognito_Extended-0.2.7.dist-info/top_level.txt
Flask_Cognito_Extended-0.2.7.dist-info/RECORD
