Metadata-Version: 2.1
Name: Flask-Cognito-Extended
Version: 0.2.7
Summary: Extended Cognito integration with Flask
Home-page: https://github.com/deejungx/flask-cognito-extended
Author: Dipesh Jung Pandey
Author-email: dipzz1394@gmail.com
License: MIT
Keywords: flask,amazon cognito,json web token
Platform: any
Classifier: Development Status :: 4 - Beta
Classifier: Environment :: Web Environment
Classifier: Framework :: Flask
Classifier: Intended Audience :: Developers
Classifier: License :: OSI Approved :: MIT License
Classifier: Operating System :: OS Independent
Classifier: Programming Language :: Python :: 3.5
Classifier: Programming Language :: Python :: 3.6
Classifier: Programming Language :: Python :: 3.7
Classifier: Programming Language :: Python :: 3.8
Classifier: Topic :: Internet :: WWW/HTTP :: Dynamic Content
Classifier: Topic :: Software Development :: Libraries :: Python Modules
Classifier: Topic :: Software Development :: Version Control :: Git
Classifier: Topic :: System :: Systems Administration :: Authentication/Directory
Requires-Dist: Flask (<2.0,>=1.0)
Requires-Dist: python-jose[cryptography] (>=3.1.0)
Requires-Dist: PyJWT (<2.0,>=1.7)
Requires-Dist: requests (<3.0.0,>=2.9.1)
